cadence_flow/__init__.py
cadence_flow/main.py
cadence_flow/models.py
cadence_flow/websocket.py
cadence_flow-0.0.1.dev0.dist-info/licenses/LICENSE
cadence_flow-0.0.1.dev0.dist-info/METADATA
cadence_flow-0.0.1.dev0.dist-info/WHEEL
cadence_flow-0.0.1.dev0.dist-info/top_level.txt
cadence_flow-0.0.1.dev0.dist-info/RECORD
