Metadata-Version: 2.4
Name: cadence-flow
Version: 0.0.1.dev0
Summary: Placeholder for the Cadence Flow project. An open-source Python library for human-in-the-loop AI workflows.
Author-email: The Cadence Flow Authors <contact@cadence-flow.com>
License: MIT License
Project-URL: Homepage, https://github.com/cadence-flow
Project-URL: Bug Tracker, https://github.com/cadence-flow/cadence-flow/issues
Project-URL: Source, https://github.com/cadence-flow
Classifier: Development Status :: 1 - Planning
Classifier: Intended Audience :: Developers
Classifier: License :: OSI Approved :: MIT License
Classifier: Programming Language :: Python :: 3
Classifier: Operating System :: OS Independent
Classifier: Topic :: Software Development :: Libraries :: Python Modules
Classifier: Topic :: Scientific/Engineering :: Artificial Intelligence
Requires-Python: >=3.9
License-File: LICENSE
Dynamic: license-file
